LICENSE
MANIFEST.in
README.rst
setup.py
isochrones/__init__.py
isochrones/bc.py
isochrones/cluster.py
isochrones/cluster_utils.py
isochrones/config.py
isochrones/eep.py
isochrones/extinction.py
isochrones/fit.py
isochrones/grid.py
isochrones/interp.py
isochrones/isochrone.py
isochrones/likelihood.py
isochrones/logger.py
isochrones/mags.py
isochrones/models.py
isochrones/observation.py
isochrones/populations.py
isochrones/priors.py
isochrones/starfit.py
isochrones/starmodel.py
isochrones/summary.py
isochrones/utils.py
isochrones/version.py
isochrones.egg-info/PKG-INFO
isochrones.egg-info/SOURCES.txt
isochrones.egg-info/dependency_links.txt
isochrones.egg-info/not-zip-safe
isochrones.egg-info/requires.txt
isochrones.egg-info/top_level.txt
isochrones/mist/__init__.py
isochrones/mist/bc.py
isochrones/mist/eep.py
isochrones/mist/isochrone.py
isochrones/mist/models.py
isochrones/mist/utils.py
isochrones/query/__init__.py
isochrones/query/catalog.py
isochrones/query/query.py
isochrones/query/vizier.py
isochrones/tests/__init__.py
isochrones/tests/test_basic.py
isochrones/tests/test_fits.py
isochrones/tests/test_ini.py
isochrones/tests/test_interp.py
isochrones/tests/test_likelihood.py
isochrones/tests/test_populations.py
isochrones/tests/test_priors.py
isochrones/tests/test_query.py
isochrones/tests/tests.py
isochrones/tests/star1/star.ini
isochrones/tests/star2/star.ini
isochrones/tests/star3/star.ini
isochrones/tests/star4/star.ini
scripts/batch_starfit
scripts/isochrones-dartmouth_write_tri
scripts/mist-initialize.py
scripts/starfit
scripts/starfit-summarize
scripts/starmodel-select