Metadata-Version: 1.1
Name: isochrones
Version: 2.1
Summary: Defines objects for interpolating stellar model grids.
Home-page: https://github.com/timothydmorton/isochrones
Author: Timothy D. Morton
Author-email: tim.morton@gmail.com
License: UNKNOWN
Platform: UNKNOWN
Classifier: Development Status :: 3 - Alpha
Classifier: Intended Audience :: Science/Research
Classifier: Operating System :: OS Independent
Classifier: Programming Language :: Python
Classifier: Topic :: Scientific/Engineering :: Astronomy
